katch/__init__.py
katch/catcher.py
katch/scenario.py
katch-0.0.3.dist-info/LICENSE
katch-0.0.3.dist-info/METADATA
katch-0.0.3.dist-info/WHEEL
katch-0.0.3.dist-info/top_level.txt
katch-0.0.3.dist-info/RECORD
